Metadata-Version: 2.1
Name: HtmlLive
Version: 0.0.1
Summary: A lightweight website creator
Home-page: UNKNOWN
Author: NiekHM
Author-email: 524712@edu.laarenberg.nl
License: MIT
Keywords: website
Platform: UNKNOWN
Classifier: Development Status :: 5 - Production/Stable
Classifier: Intended Audience :: Education
Classifier: Operating System :: Microsoft :: Windows :: Windows 10
Classifier: License :: OSI Approved :: MIT License
Classifier: Programming Language :: Python :: 3
License-File: LICENCE.txt
